tastymap/__init__.py
tastymap/ai.py
tastymap/cli.py
tastymap/core.py
tastymap/models.py
tastymap/ui.py
tastymap/utils.py
tastymap-0.4.1.dist-info/METADATA
tastymap-0.4.1.dist-info/WHEEL
tastymap-0.4.1.dist-info/entry_points.txt
tastymap-0.4.1.dist-info/licenses/LICENSE
tastymap-0.4.1.dist-info/RECORD
