Metadata-Version: 2.1
Name: tastymap
Version: 0.4.1
Summary: Color palettes for your palate
Project-URL: Documentation, https://ahuang11.github.io/tastymap/
Project-URL: Source, https://github.com/ahuang11/tastymap
Author: tastymap
License-File: LICENSE
Classifier: Programming Language :: Python :: 3 :: Only
Requires-Python: >=3.9
Requires-Dist: matplotlib
Requires-Dist: numpy
Provides-Extra: ai
Requires-Dist: marvin; extra == 'ai'
Requires-Dist: pydantic; extra == 'ai'
Provides-Extra: ui
Requires-Dist: netcdf4; extra == 'ui'
Requires-Dist: panel; extra == 'ui'
Requires-Dist: param; extra == 'ui'
Requires-Dist: pooch; extra == 'ui'
Requires-Dist: requests; extra == 'ui'
Requires-Dist: xarray; extra == 'ui'
